WebGestaltPy-0.3.2.dist-info/METADATA
WebGestaltPy-0.3.2.dist-info/WHEEL
WebGestaltPy-0.3.2.dist-info/licenses/LICENSE
webgestaltpy.libs/libgcc_s-e52197c3.so.1
webgestaltpy/__init__.py
webgestaltpy/webgestaltpy.cpython-313-aarch64-linux-musl.so
WebGestaltPy-0.3.2.dist-info/RECORD
